stui/__init__.py
stui/backend.py
stui/cli.py
stui/stui.py
stui/widgets.py
stui/views/__init__.py
stui/views/admin.py
stui/views/jobs.py
stui/views/nodes.py
stui-0.3.6.dist-info/LICENSE
stui-0.3.6.dist-info/METADATA
stui-0.3.6.dist-info/WHEEL
stui-0.3.6.dist-info/entry_points.txt
stui-0.3.6.dist-info/top_level.txt
stui-0.3.6.dist-info/RECORD
