Metadata-Version: 2.1
Name: stui
Version: 0.3.6
Summary: A Slurm client for the terminal
Home-page: https://github.com/mi-lad/stui
Author: Milad Alizadeh
Author-email: m@mil.ad
License: UNKNOWN
Keywords: slurm,cluster
Platform: UNKNOWN
Classifier: Intended Audience :: Developers
Classifier: License :: OSI Approved :: MIT License
Requires-Python: >=3.6
Requires-Dist: urwid
Requires-Dist: fabric (>=2.5.0)
